waygrounddocgen/__init__.py
waygrounddocgen/cli.py
waygrounddocgen/eval/__init__.py
waygrounddocgen/eval/config.yaml
waygrounddocgen/eval/evaluator.py
waygrounddocgen/eval/checks/__init__.py
waygrounddocgen/eval/checks/coverage.py
waygrounddocgen/eval/checks/freshness.py
waygrounddocgen/eval/checks/structure.py
waygrounddocgen/eval/llm_judge/__init__.py
waygrounddocgen/eval/llm_judge/judge.py
waygrounddocgen/eval/llm_judge/prompts/accuracy.md
waygrounddocgen/eval/llm_judge/prompts/clarity.md
waygrounddocgen/eval/llm_judge/prompts/completeness.md
waygrounddocgen/eval/retry/__init__.py
waygrounddocgen/eval/retry/feedback_loop.py
waygrounddocgen/prompts/comprehensive.md
waygrounddocgen/prompts/discover.md
waygrounddocgen/prompts/generate_doc.md
waygrounddocgen-0.2.0.dist-info/licenses/LICENSE
waygrounddocgen-0.2.0.dist-info/METADATA
waygrounddocgen-0.2.0.dist-info/WHEEL
waygrounddocgen-0.2.0.dist-info/entry_points.txt
waygrounddocgen-0.2.0.dist-info/top_level.txt
waygrounddocgen-0.2.0.dist-info/RECORD
