Metadata-Version: 2.4
Name: waygrounddocgen
Version: 0.2.0
Summary: A language-agnostic documentation generator and evaluator using Cursor AI
Author: Gaurav Madan
License-Expression: MIT
Project-URL: Homepage, https://github.com/gauravmadan/waygrounddocgen
Project-URL: Repository, https://github.com/gauravmadan/waygrounddocgen
Project-URL: Issues, https://github.com/gauravmadan/waygrounddocgen/issues
Keywords: documentation,cursor,ai,docgen,automation,cli,evaluation
Classifier: Development Status :: 4 - Beta
Classifier: Environment :: Console
Classifier: Intended Audience :: Developers
Classifier: Operating System :: MacOS
Classifier: Operating System :: POSIX :: Linux
Classifier: Programming Language :: Python :: 3
Classifier: Programming Language :: Python :: 3.8
Classifier: Programming Language :: Python :: 3.9
Classifier: Programming Language :: Python :: 3.10
Classifier: Programming Language :: Python :: 3.11
Classifier: Programming Language :: Python :: 3.12
Classifier: Topic :: Documentation
Classifier: Topic :: Software Development :: Documentation
Classifier: Topic :: Utilities
Requires-Python: >=3.8
License-File: LICENSE
Requires-Dist: importlib-resources>=5.0; python_version < "3.9"
Provides-Extra: eval
Requires-Dist: anthropic>=0.18.0; extra == "eval"
Requires-Dist: pyyaml>=6.0; extra == "eval"
Provides-Extra: dev
Requires-Dist: build; extra == "dev"
Requires-Dist: twine; extra == "dev"
Requires-Dist: pytest; extra == "dev"
Provides-Extra: all
Requires-Dist: waygrounddocgen[dev,eval]; extra == "all"
Dynamic: license-file
